linpgtoolbox/CODE_OF_CONDUCT.md
linpgtoolbox/LICENSE
linpgtoolbox/README.md
linpgtoolbox/__init__.py
linpgtoolbox/_compiler.py
linpgtoolbox/_execute.py
linpgtoolbox/_fixer.py
linpgtoolbox/builder.py
linpgtoolbox/cli.py
linpgtoolbox/organizer.py
linpgtoolbox/pkginstaller.py
linpgtoolbox/py.typed
linpgtoolbox/pyinstaller.py
linpgtoolbox/__pyinstaller/__init__.py
linpgtoolbox/__pyinstaller/hook.py
linpgtoolbox-25.11.dist-info/licenses/LICENSE
linpgtoolbox-25.11.dist-info/METADATA
linpgtoolbox-25.11.dist-info/WHEEL
linpgtoolbox-25.11.dist-info/entry_points.txt
linpgtoolbox-25.11.dist-info/top_level.txt
linpgtoolbox-25.11.dist-info/RECORD
