Metadata-Version: 2.4
Name: linpgtoolbox
Version: 25.11
Summary: A set of tools for managing, compiling, and uploading your own package.
Author-email: Linpg Foundation <yudong9912@gmail.com>
Project-URL: Bug Tracker, https://github.com/LinpgFoundation/linpg-toolbox/issues
Project-URL: Homepage, https://github.com/LinpgFoundation/linpg-toolbox
Classifier: Operating System :: OS Independent
Classifier: Programming Language :: Python :: 3.11
Classifier: Programming Language :: Python :: 3.12
Classifier: Programming Language :: Python :: 3.13
Classifier: Programming Language :: Python :: 3.14
Classifier: Programming Language :: Python :: Implementation :: CPython
Requires-Python: >=3.11
License-File: LICENSE
Requires-Dist: mypy
Dynamic: license-file
